pydomains/__init__.py
pydomains/dmoz_cat.py
pydomains/phish_cat.py
pydomains/pred_malware.py
pydomains/pred_phish.py
pydomains/pred_shalla.py
pydomains/pred_toulouse.py
pydomains/shalla_cat.py
pydomains/utils.py
pydomains/examples/input-header.csv
pydomains/examples/input-noheader.csv
pydomains/tests/__init__.py
pydomains/tests/test_010_shalla_cat.py
pydomains/tests/test_020_pred_toulouse.py
pydomains-0.2.0.dist-info/LICENSE
pydomains-0.2.0.dist-info/METADATA
pydomains-0.2.0.dist-info/WHEEL
pydomains-0.2.0.dist-info/entry_points.txt
pydomains-0.2.0.dist-info/top_level.txt
pydomains-0.2.0.dist-info/RECORD
