Metadata-Version: 2.1
Name: pydomains
Version: 0.2.0
Summary: Classifying the Content of Domains
Home-page: https://github.com/themains/pydomains
Author: Suriyan Laohaprapanon, Gaurav Sood
Author-email: suriyant@gmail.com, gsood07@gmail.com
License: MIT
Keywords: domain dmoz shalla phishing malware lstm
Platform: UNKNOWN
Classifier: Development Status :: 3 - Alpha
Classifier: Intended Audience :: Developers
Classifier: License :: OSI Approved :: MIT License
Classifier: Programming Language :: Python :: 2.7
Classifier: Programming Language :: Python :: 3.5
Classifier: Programming Language :: Python :: 3.6
Classifier: Programming Language :: Python :: 3.7
Classifier: Topic :: Scientific/Engineering :: Information Analysis
Classifier: Topic :: Software Development :: Libraries :: Python Modules
Classifier: Topic :: Utilities
Requires-Dist: pandas
Requires-Dist: tldextract
Requires-Dist: requests
Requires-Dist: tqdm
Requires-Dist: h5py
Requires-Dist: keras
Requires-Dist: tensorflow
Provides-Extra: dev
Requires-Dist: check-manifest ; extra == 'dev'
Provides-Extra: test
Requires-Dist: coverage ; extra == 'test'
